matrix_reportbot/__init__.py
matrix_reportbot/__main__.py
matrix_reportbot/classes/__init__.py
matrix_reportbot/classes/bot.py
matrix_reportbot/classes/logging.py
matrix_reportbot-0.0.3.dist-info/METADATA
matrix_reportbot-0.0.3.dist-info/WHEEL
matrix_reportbot-0.0.3.dist-info/entry_points.txt
matrix_reportbot-0.0.3.dist-info/licenses/LICENSE
matrix_reportbot-0.0.3.dist-info/RECORD
