Metadata-Version: 2.3
Name: matrix-reportbot
Version: 0.0.3
Summary: Simple content report subscription bot for Matrix.
Project-URL: Homepage, https://git.private.coffee/PrivateCoffee/matrix-reportbot
Project-URL: Bug Tracker, https://git.private.coffee/PrivateCoffee/matrix-reportbot/issues
Author-email: "Private.coffee Team" <support@private.coffee>
License: Copyright (c) 2024 Private.coffee Team <support@private.coffee>
License-File: LICENSE
Classifier: License :: OSI Approved :: MIT License
Classifier: Operating System :: OS Independent
Classifier: Programming Language :: Python :: 3
Requires-Python: >=3.10
Requires-Dist: markdown2
Requires-Dist: matrix-nio
Requires-Dist: setuptools
